{"cameraMode":{"drawMode":0,"name":"Shaded","section":"Shading Mode"},"sceneLighting":true,"audioPlay":false,"sceneViewState":{"showFog":true,"showMaterialUpdate":false,"showSkybox":true,"showFlares":true,"showImageEffects":true,"showParticleSystems":true},"in2DMode":false,"pivot":{"x":-0.6085147857666016,"y":1.823575735092163,"z":24.792856216430665},"rotation":{"x":0.13090483844280244,"y":-0.48225370049476626,"z":0.07276849448680878,"w":0.86333829164505},"size":2.3750462532043459,"orthographic":false}